{
    "Name": "CommonLanguage",
    "Subsets": [],
    "HF Link": "https://hf.co/datasets/anton-l/common_language",
    "Link": "https://github.com/speechbrain/speechbrain/tree/develop/recipes/CommonLanguage",
    "License": "CC BY 4.0",
    "Year": 2021,
    "Language": "multilingual",
    "Dialect": "ar-MSA: (Arabic (Modern Standard Arabic))",
    "Domain": "transcribed audio",
    "Form": "spoken",
    "Collection Style": "other",
    "Description": "This dataset is composed of speech recordings from languages that were carefully selected from the CommonVoice database. The total duration of audio recordings is 45.1 hours (i.e., 1 hour of material for each language). The dataset has been extracted from CommonVoice to train language-id systems.",
    "Volume": "1",
    "Unit": "hours",
    "Ethical Risks": "Low",
    "Provider": " SpeechBrain",
    "Derived From": "CommonVoice",
    "Paper Title": "nan",
    "Paper Link": "nan",
    "Script": "Arab",
    "Tokenized": "No",
    "Host": "GitHub",
    "Access": "Free",
    "Cost": "nan",
    "Test Split": "No",
    "Tasks": "speech recognition",
    "Venue Title": "nan",
    "Citations": "nan",
    "Venue Type": "nan",
    "Venue Name": "nan",
    "Authors": "nan",
    "Affiliations": "nan",
    "Abstract": "nan",
    "Added By": "Zaid Alyafeai"
}