{
    "Name": "Dataset for evaluating root extraction",
    "Subsets": [],
    "HF Link": "https://hf.co/datasets/arbml/root_extraction_vaidation",
    "Link": "https://github.com/arabic-digital-humanities/root-extraction-validation-data",
    "License": "CC BY 4.0",
    "Year": 2018,
    "Language": "ar",
    "Dialect": "ar-MSA: (Arabic (Modern Standard Arabic))",
    "Domain": "other",
    "Form": "text",
    "Collection Style": "other",
    "Description": "This dataset contains data to evaluate the roots extracted by Arabic stemmers and morphological analyzers.",
    "Volume": "2,962",
    "Unit": "tokens",
    "Ethical Risks": "Low",
    "Provider": "nan",
    "Derived From": "OpenITI project",
    "Paper Title": "nan",
    "Paper Link": "nan",
    "Script": "Arab",
    "Tokenized": "No",
    "Host": "GitHub",
    "Access": "Free",
    "Cost": "nan",
    "Test Split": "No",
    "Tasks": "lemmatization ",
    "Venue Title": "nan",
    "Citations": "nan",
    "Venue Type": "nan",
    "Venue Name": "nan",
    "Authors": "nan",
    "Affiliations": "nan",
    "Abstract": "nan",
    "Added By": "Zaid Alyafeai"
}