{
    "Name": "KSUEmotions",
    "Subsets": [],
    "HF Link": "",
    "Link": "https://catalog.ldc.upenn.edu/LDC2017S12",
    "License": "LDC User Agreement",
    "Year": 2017,
    "Language": "ar",
    "Dialect": "Modern Standard Arabic",
    "Domain": [
        "news articles"
    ],
    "Form": "audio",
    "Collection Style": [
        "human annotation"
    ],
    "Description": "Audio was recorded in each participant's home. Audio is presented as 16-bit 16 kHz flac compressed wav. In addition to speech files and metadata about the speakers, timeless label files and automatic time segmentation alignment files are included. Text is presented as UTF-8 plain text.",
    "Volume": 5.0,
    "Unit": "hours",
    "Ethical Risks": "Low",
    "Provider": [
        "King Saud University"
    ],
    "Derived From": [],
    "Paper Title": "",
    "Paper Link": "",
    "Script": "Arab",
    "Tokenized": false,
    "Host": "LDC",
    "Access": "With-Fee",
    "Cost": "1,000.00 $",
    "Test Split": false,
    "Tasks": [
        "speech recognition",
        "emotion classification"
    ],
    "Venue Title": "",
    "Venue Type": "",
    "Venue Name": "",
    "Authors": [
        "Ali Hamid Meftah",
        "Yousef Ajami Alotaibi",
        "Sid-Ahmed Selouani"
    ],
    "Affiliations": [
        "King Saud University"
    ],
    "Abstract": "",
    "Added By": "Zaid Alyafeai"
}