{
    "Name": "Multilingual Dictionary of Sports: \u2013 English-French-Arabic trilingual database",
    "Subsets": [],
    "HF Link": "",
    "Link": "https://catalogue.elra.info/en-us/repository/browse/ELRA-T0372_04/",
    "License": "Non Commercial Use - ELRA END USER",
    "Year": 2009,
    "Language": "multilingual",
    "Dialect": "Modern Standard Arabic",
    "Domain": [
        "other"
    ],
    "Form": "text",
    "Collection Style": [
        "other"
    ],
    "Description": "This dictionary was produced within the French national project EuRADic (European and Arabic Dictionaries and Corpora), as part of the Technolangue programme funded by the French Ministry of Industry.",
    "Volume": 40000.0,
    "Unit": "tokens",
    "Ethical Risks": "Low",
    "Provider": [
        "French Ministry of Industry"
    ],
    "Derived From": [],
    "Paper Title": "",
    "Paper Link": "",
    "Script": "Arab",
    "Tokenized": false,
    "Host": "ELRA",
    "Access": "With-Fee",
    "Cost": "200.00\u20ac",
    "Test Split": false,
    "Tasks": [
        "dictionary"
    ],
    "Venue Title": "",
    "Venue Type": "conference",
    "Venue Name": "",
    "Authors": [],
    "Affiliations": [],
    "Abstract": "",
    "Added By": "Zaid Alyafeai"
}