{
    "Name": "SVQ",
    "Dialect Subsets": [
        {
            "Name": "ar_eg",
            "Volume": 18.23,
            "Unit": "hours",
            "Dialect": "Egypt"
        },
        {
            "Name": "ar_x_gulf",
            "Volume": 17.78,
            "Unit": "hours",
            "Dialect": "Gulf"
        },
        {
            "Name": "ar_x_levant",
            "Volume": 14.13,
            "Unit": "hours",
            "Dialect": "Levant"
        },
        {
            "Name": "ar_x_maghrebi",
            "Volume": 17.39,
            "Unit": "hours",
            "Dialect": "North Africa"
        }
    ],
    "HF Link": "https://huggingface.co/datasets/google/svq",
    "Link": "https://huggingface.co/datasets/google/svq",
    "License": "CC BY 4.0",
    "Year": 2025,
    "Language": "multilingual",
    "Dialect": "mixed",
    "Source": [
        "public datasets"
    ],
    "Domain": [
        "general"
    ],
    "Form": "audio",
    "Collection Style": [
        "human annotation"
    ],
    "Description": "Simple Voice Questions (SVQ) is a set of short audio questions recorded in 26 locales across 17 languages under multiple audio conditions.",
    "Volume": 67.52,
    "Unit": "hours",
    "Ethical Risks": "Low",
    "Provider": [
        "Google"
    ],
    "Derived From": [
        " XTREME-UP"
    ],
    "Paper Title": "",
    "Paper Link": "",
    "Script": "Arab",
    "Tokenized": false,
    "Host": "HuggingFace",
    "Access": "Free",
    "Cost": "",
    "Has Splits": false,
    "Partial": false,
    "Tasks": [
        "speech recognition"
    ],
    "Venue Title": "",
    "Venue Type": "other",
    "Venue Name": "",
    "Authors": [],
    "Affiliations": [],
    "Abstract": "",
    "Added By": "Zaid Alyafeai"
}
